[
  {
    "title": "Polícia Militar do Estado de São Paulo",
    "slug": "pm-sp",
    "highlight": "Formação completa com foco em condicionamento físico, legislação e simulados semanais.",
    "salary": "Até R$ 6.882,21",
    "opportunities": "1.200 vagas previstas",
    "badge": "Em alta",
    "featured": true,
    "cta": "Ver cursos disponíveis",
    "url": "https://exemplo.com/pm-sp",
    "questions": 342,
    "comments": 58,
    "priority": 5,
    "categories": ["Segurança Pública"],
    "boards": ["Vunesp"]
  },
  {
    "title": "Instituto Nacional do Seguro Social",
    "slug": "inss-analista",
    "highlight": "Aulas atualizadas sobre previdência, direito administrativo e raciocínio lógico.",
    "salary": "Até R$ 8.984,81",
    "opportunities": "Concurso nacional",
    "badge": "Atualizado",
    "featured": true,
    "cta": "Montar plano de estudos",
    "url": "https://exemplo.com/inss",
    "questions": 410,
    "comments": 72,
    "priority": 4,
    "categories": ["Administrativo"],
    "boards": ["Cebraspe"]
  },
  {
    "title": "Departamento de Polícia Federal",
    "slug": "pf-agente",
    "highlight": "Trilhas estratégicas com resolução de casos práticos, inteligência e legislação penal.",
    "salary": "Até R$ 12.522,50",
    "opportunities": "Vagas em todo o Brasil",
    "badge": "Inscrições abertas",
    "featured": true,
    "cta": "Quero me preparar",
    "url": "https://exemplo.com/pf",
    "questions": 368,
    "comments": 64,
    "priority": 6,
    "categories": ["Segurança Pública"],
    "boards": ["Cebraspe"]
  },
  {
    "title": "Banco do Brasil",
    "slug": "bb-escriturario",
    "highlight": "Foco em vendas consultivas, matemática financeira e atualidades do mercado financeiro.",
    "salary": "Até R$ 5.436,00",
    "opportunities": "Cadastro nacional",
    "badge": "Favorito",
    "featured": false,
    "cta": "Começar agora",
    "url": "https://exemplo.com/bb",
    "questions": 295,
    "comments": 51,
    "priority": 3,
    "categories": ["Instituições Financeiras"],
    "boards": ["Fundação Cesgranrio"]
  },
  {
    "title": "Tribunal de Justiça do Rio de Janeiro",
    "slug": "tj-rj",
    "highlight": "Mentorias de peças processuais, língua portuguesa e administração judiciária.",
    "salary": "Até R$ 9.072,05",
    "opportunities": "Concursos regionais",
    "badge": "Novidade",
    "featured": false,
    "cta": "Explorar turmas",
    "url": "https://exemplo.com/tjrj",
    "questions": 312,
    "comments": 39,
    "priority": 2,
    "categories": ["Tribunais"],
    "boards": ["FGV"]
  }
]
